{
  "project_info": {
    "project_number": "1027518034716",
    "project_id": "finalproject-24728",
    "storage_bucket": "finalproject-24728.appspot.com"
  },
  "client": [
    {
      "client_info": {
        "mobilesdk_app_id": "1:1027518034716:android:f75360f5b69f347fac40d9",
        "android_client_info": {
          "package_name": "com.example.efarms"
        }
      },
      "oauth_client": [
        {
          "client_id": "1027518034716-gffoqkr4km14retumj5safcoe65b4tr5.apps.googleusercontent.com",
          "client_type": 3
        }
      ],
      "api_key": [
        {
          "current_key": "AIzaSyAQ6RQcMILNKuNBCro7pRonvz2pRMGmgyQ"
        }
      ],
      "services": {
        "appinvite_service": {
          "other_platform_oauth_client": [
            {
              "client_id": "1027518034716-gffoqkr4km14retumj5safcoe65b4tr5.apps.googleusercontent.com",
              "client_type": 3
            },
            {
              "client_id": "1027518034716-cmi5nbvei28hr9c75pgmiuu5qs9i787d.apps.googleusercontent.com",
              "client_type": 2,
              "ios_info": {
                "bundle_id": "com.example.efarms"
              }
            }
          ]
        }
      }
    },
    {
      "client_info": {
        "mobilesdk_app_id": "1:1027518034716:android:b5b4d5d9a77f1240ac40d9",
        "android_client_info": {
          "package_name": "com.example.final_project"
        }
      },
      "oauth_client": [
        {
          "client_id": "1027518034716-gmkfaakbb0837ha99quccodgsfg0cs33.apps.googleusercontent.com",
          "client_type": 1,
          "android_info": {
            "package_name": "com.example.final_project",
            "certificate_hash": "54897bfa63dd642ca19f0e6a9ccb9a670cc7ca83"
          }
        },
        {
          "client_id": "1027518034716-gffoqkr4km14retumj5safcoe65b4tr5.apps.googleusercontent.com",
          "client_type": 3
        }
      ],
      "api_key": [
        {
          "current_key": "AIzaSyAQ6RQcMILNKuNBCro7pRonvz2pRMGmgyQ"
        }
      ],
      "services": {
        "appinvite_service": {
          "other_platform_oauth_client": [
            {
              "client_id": "1027518034716-gffoqkr4km14retumj5safcoe65b4tr5.apps.googleusercontent.com",
              "client_type": 3
            },
            {
              "client_id": "1027518034716-cmi5nbvei28hr9c75pgmiuu5qs9i787d.apps.googleusercontent.com",
              "client_type": 2,
              "ios_info": {
                "bundle_id": "com.example.efarms"
              }
            }
          ]
        }
      }
    }
  ],
  "configuration_version": "1"
}